sjbillingclient/__init__.py
sjbillingclient/jclass/__init__.py
sjbillingclient/jclass/acknowledge.py
sjbillingclient/jclass/billing.py
sjbillingclient/jclass/consume.py
sjbillingclient/jclass/purchase.py
sjbillingclient/jclass/queryproduct.py
sjbillingclient/jinterface/__init__.py
sjbillingclient/jinterface/acknowledge.py
sjbillingclient/jinterface/billing.py
sjbillingclient/jinterface/consume.py
sjbillingclient/jinterface/product.py
sjbillingclient/jinterface/purchases.py
sjbillingclient/tools/__init__.py
sjbillingclient-0.1.2.dist-info/METADATA
sjbillingclient-0.1.2.dist-info/WHEEL
sjbillingclient-0.1.2.dist-info/RECORD
